SIGMA/pe.v
`timescale 1ns / 1ps
module pe #(
     parameter   DATA_WIDTH  = 32
     )
        (   input reset_accumulator,
            input clk,
            input [DATA_WIDTH-1:0] input_top,
            input [DATA_WIDTH-1:0] input_left,
            output [DATA_WIDTH-1:0] output_bottom,
            output [DATA_WIDTH-1:0] output_right
        );
   
    reg [DATA_WIDTH-1:0] output_bottom_reg=0;
    reg [DATA_WIDTH-1:0] output_right_reg=0;
    reg [DATA_WIDTH-1:0] accumulator=0;
//    wire [DATA_WIDTH-1:0] accumulatorx = 
    //wire [DATA_WIDTH-1:0] output_accumulator;

    assign output_right=output_right_reg;
    assign output_bottom=output_bottom_reg;
    
//    always @(posedge clk) begin
//        if(reset_accumulator==1)
//            begin
//                accumulator <= 0;
//            end
//        else  
//            begin
////                $display("what is this %d %d %d",$time,input_top,input_left);
//                accumulator <= accumulator + (input_top*input_left); //accumulator + (input_top*input_left);
//            end
//    end

    always @(posedge clk) begin
        if(reset_accumulator)
        begin
            output_bottom_reg <= 0;
            output_right_reg  <= 0;
        end
        else
        begin
            output_bottom_reg <= input_top;
            output_right_reg  <= input_left;
        end
    end
endmodule

SIGMA/pearray2X2.v
`timescale 1ns / 1ps
module pearray4X4 #
        (
            parameter DATA_WIDTH=16,
            parameter NUM_PES=16
        )
        (input clk,
        input reset,
        input [DATA_WIDTH-1:0] in1,
        input [DATA_WIDTH-1:0] in2,
        input [DATA_WIDTH-1:0] in3,
        input [DATA_WIDTH-1:0] in4,
        input [DATA_WIDTH-1:0] in5,
        input [DATA_WIDTH-1:0] in6,
        input [DATA_WIDTH-1:0] in7,
        input [DATA_WIDTH-1:0] in8,


        output [DATA_WIDTH-1:0] out1,
        output [DATA_WIDTH-1:0] out2,
        output [DATA_WIDTH-1:0] out3,
        output [DATA_WIDTH-1:0] out4        
        );
    wire [DATA_WIDTH-1:0] penet[NUM_PES*2:0];
    assign out1 = penet[7];
    assign out2 = penet[15];
    assign out3 = penet[23];
    assign out4 = penet[31];
    integer k;
//    always@(reset)
//    begin
//        for(k = 0; k<DATA_WIDTH; k = k+1)begin
//            penet[k] = 0;
//        end 
//    end
    pe #(.DATA_WIDTH(DATA_WIDTH))
     pe11
    (    .reset_accumulator(reset),
         .clk(clk),
         .input_top(in5),
         .input_left(in1),
         .output_bottom(penet[1]),
         .output_right(penet[0])
    );
    pe #(.DATA_WIDTH(DATA_WIDTH))
     pe21
    (    .reset_accumulator(reset),
         .clk(clk),
         .input_top(penet[1]),
         .input_left(in2),
         .output_bottom(penet[3]),
         .output_right(penet[2])
    );
    pe #(.DATA_WIDTH(DATA_WIDTH))
     pe31
    (    .reset_accumulator(reset),
         .clk(clk),
         .input_top(penet[3]),
         .input_left(in3),
         .output_bottom(penet[5]),
         .output_right(penet[4])
    );
    pe #(.DATA_WIDTH(DATA_WIDTH))
     pe41
    (    .reset_accumulator(reset),
         .clk(clk),
         .input_top(penet[5]),
         .input_left(in4),
         .output_bottom(penet[7]),
         .output_right(penet[6])
    );
    pe #(.DATA_WIDTH(DATA_WIDTH))
     pe12
    (    .reset_accumulator(reset),
         .clk(clk),
         .input_top(in6),
         .input_left(penet[0]),
         .output_bottom(penet[9]),
         .output_right(penet[8])
    );
    pe #(.DATA_WIDTH(DATA_WIDTH))
     pe22
    (    .reset_accumulator(reset),
         .clk(clk),
         .input_top(penet[9]),
         .input_left(penet[2]),
         .output_bottom(penet[11]),
         .output_right(penet[10])
    );
    pe #(.DATA_WIDTH(DATA_WIDTH))
     pe32
    (    .reset_accumulator(reset),
         .clk(clk),
         .input_top(penet[11]),
         .input_left(penet[4]),
         .output_bottom(penet[13]),
         .output_right(penet[12])
    );
    pe #(.DATA_WIDTH(DATA_WIDTH))
     pe42
    (    .reset_accumulator(reset),
         .clk(clk),
         .input_top(penet[13]),
         .input_left(penet[6]),
         .output_bottom(penet[15]),
         .output_right(penet[14])
    );
    pe #(.DATA_WIDTH(DATA_WIDTH))
     pe13
    (    .reset_accumulator(reset),
         .clk(clk),
         .input_top(in7),
         .input_left(penet[8]),
         .output_bottom(penet[17]),
         .output_right(penet[16])
    );
    pe #(.DATA_WIDTH(DATA_WIDTH))
     pe23
    (    .reset_accumulator(reset),
         .clk(clk),
         .input_top(penet[17]),
         .input_left(penet[10]),
         .output_bottom(penet[19]),
         .output_right(penet[18])
    );
    pe #(.DATA_WIDTH(DATA_WIDTH))
     pe33
    (    .reset_accumulator(reset),
         .clk(clk),
         .input_top(penet[19]),
         .input_left(penet[12]),
         .output_bottom(penet[21]),
         .output_right(penet[20])
    );
    pe #(.DATA_WIDTH(DATA_WIDTH))
     pe43
    (    .reset_accumulator(reset),
         .clk(clk),
         .input_top(penet[21]),
         .input_left(penet[14]),
         .output_bottom(penet[23]),
         .output_right(penet[22])
    );
    pe #(.DATA_WIDTH(DATA_WIDTH))
     pe14
    (    .reset_accumulator(reset),
         .clk(clk),
         .input_top(in8),
         .input_left(penet[16]),
         .output_bottom(penet[25]),
         .output_right(penet[24])
    );
    pe #(.DATA_WIDTH(DATA_WIDTH))
     pe24
    (    .reset_accumulator(reset),
         .clk(clk),
         .input_top(penet[25]),
         .input_left(penet[18]),
         .output_bottom(penet[27]),
         .output_right(penet[26])
    );
    pe #(.DATA_WIDTH(DATA_WIDTH))
     pe34
    (    .reset_accumulator(reset),
         .clk(clk),
         .input_top(penet[27]),
         .input_left(penet[20]),
         .output_bottom(penet[29]),
         .output_right(penet[28])
    );
    pe #(.DATA_WIDTH(DATA_WIDTH))
     pe44
    (    .reset_accumulator(reset),
         .clk(clk),
         .input_top(penet[29]),
         .input_left(penet[22]),
         .output_bottom(penet[31]),
         .output_right(penet[30])
    );
endmodule

SIGMA/pearray_tb.v
`timescale 1ns / 1ps

module pearray_tb;

parameter DATA_WIDTH=32;
parameter NUM_PES=16;
reg clk=1;
reg reset=0;

reg [DATA_WIDTH-1:0] in1;
reg [DATA_WIDTH-1:0] in2;
reg [DATA_WIDTH-1:0] in3;
reg [DATA_WIDTH-1:0] in4;
reg [DATA_WIDTH-1:0] in5;
reg [DATA_WIDTH-1:0] in6;
reg [DATA_WIDTH-1:0] in7;
reg [DATA_WIDTH-1:0] in8;

wire [DATA_WIDTH-1:0] out1, out2, out3, out4;

//wire [(DATA_WIDTH*16)-1:0] out;


//assign out = {out1, out2, out3, out4, out5, out6, out7, out8, out9, out10, out11, out12, out13, out14, out15, out16};
pearray4X4 #(.DATA_WIDTH(DATA_WIDTH),.NUM_PES(NUM_PES))
        uut
        (.clk(clk),
        .reset(reset),
        .in1(in1),
        .in2(in2),
        .in3(in3),
        .in4(in4),
        .in5(in5),
        .in6(in6),
        .in7(in7),
        .in8(in8),

        .out1(out1),
        .out2(out2),
        .out3(out3),
        .out4(out4)
        );
always #1 clk=~clk;

reg enable = 0,enable2= 0,enable3= 0,enable4= 0;
reg[31:0] top1,top2,top3,top4;
reg[31:0] topb1,topb2,topb3,topb4;
reg [31:0] queque1[0:3];
reg [31:0] queque2[0:3];
reg [31:0] queque3[0:3];
reg [31:0] queque4[0:3];

reg [31:0] quequeb1[0:3];
reg [31:0] quequeb2[0:3];
reg [31:0] quequeb3[0:3];
reg [31:0] quequeb4[0:3];
reg [31:0] scratchpad[0:31];
reg[1:0] counter = 0;
//reg[1:0] counter1 = 0;
always@(posedge clk)
begin
//    scratchpad[][]
    counter = counter + 1;
    if(enable && (~reset))
    begin
        in1 <= top1;
        in5 <= topb1;
    end
    else
    begin
        in1 <= 0;
        in5 <= 0;
    end
    if(enable2 && (~reset))
    begin
        in2 <= top2;
        in6 <= topb2;
    end
    else
    begin
        in2 <= 0;
        in6 <= 0;
    end
        
    if(enable3 && (~reset))
    begin
        in3 <= top3;
        in7 <= topb3;
    end
    else
    begin
        in3 <= 0;
        in7 <= 0;
    end
        
    if(enable4 && (~reset))
    begin
        in4 <= top4;
        in8 <= topb4;
    end
    else
    begin
        in4 <= 0;
        in8 <= 0;
    end

    if(counter == 7)
    begin
//        counter1 <= counter1 + 1;
        counter <= 0;
    end
    
end

always@(*)
begin
    top1 <= queque1[3];
    topb1 <= quequeb1[3];
    top2 <= queque2[3];
    topb2 <= quequeb2[3];
    top3 <= queque3[3];
    topb3 <= quequeb3[3];
    top4 <= queque4[3];
    topb4 <= quequeb4[3];
end   
//control

always@(posedge clk)
begin
    if(~reset)
    begin   
    if(counter <= 7)
        counter = counter + 1;
    else
        counter = 7;
    if(counter < 4)
     {enable,enable2,enable3,enable4} <= {1'b1,{enable,enable2,enable3}};
    else
     {enable,enable2,enable3,enable4} <= {1'b0,{enable,enable2,enable3}};
    end
    else
    begin
        counter = 0;
    end
end
integer i;
always@(posedge clk)
begin
    if(enable && (~reset)) begin
       for(i = 4; i > 0; i=i-1)
       begin
          queque1[i] <= queque1[i-1];
          quequeb1[i] <= quequeb1[i-1];
       end
       queque1[0] <= 0;
       quequeb1[0] <= 0;
    end
    if(enable2 && (~reset)) begin
       for(i = 4; i > 0; i=i-1)
       begin
          queque2[i] <= queque2[i-1];
          quequeb2[i] <= quequeb2[i-1];
       end
       queque2[0] <= 0;
       quequeb2[0] <= 0;
    end
    if(enable3 && (~reset)) begin
       for(i = 4; i > 0; i=i-1)
       begin
          queque3[i] <= queque3[i-1];
          quequeb3[i] <= quequeb3[i-1];
       end
       queque3[0] <= 0;
       quequeb3[0] <= 0;
    end
    if(enable4 && (~reset)) begin
       for(i = 4; i > 0; i=i-1)
       begin
          queque4[i] <= queque4[i-1];
          quequeb4[i] <= quequeb4[i-1];
       end
       queque4[0] <= 0;
       quequeb4[0] <= 0;
    end    
end

integer j;

initial 
    begin
    $readmemh("scratchpad.mem",scratchpad);
    $dumpfile ("pearray2.vcd");
    $dumpvars; //Dump variables in the top module.
    for(j = 3; j >= 0; j=j-1)       
    begin
     $display("j = %d",j);
     queque1[j] = scratchpad[j];end
    for(j = 3; j >= 0; j=j-1)       
        queque2[j] = scratchpad[j+4];
    for(j = 3; j >= 0; j=j-1)       
        queque3[j] = scratchpad[j+8];
    for(j = 3; j >= 0; j=j-1)       
        queque4[j] = scratchpad[j+12];
    for(j = 3; j >= 0; j=j-1)       
        quequeb1[j] = scratchpad[j+16];
    for(j = 3; j >= 0; j=j-1)       
        quequeb2[j] = scratchpad[j+20];
    for(j = 3; j >= 0; j=j-1)       
        quequeb3[j] = scratchpad[j+24];
    for(j = 3; j >= 0; j=j-1)       
        quequeb4[j] = scratchpad[j+28];
    
    $display("I am here");
    counter = 0;
    reset=1;
    #(15);
    reset=0;
    
    #120 $finish;
    end
endmodule

SIGMA/pearray.vcd
$date
	Tue Apr 13 09:27:17 2021
$end
$version
	Icarus Verilog
$end
$timescale
	1ps
$end
$scope module pearray_tb $end
$scope module uut $end
$var wire 1 ! clk $end
$var wire 32 " in1 [31:0] $end
$var wire 32 # in2 [31:0] $end
$var wire 32 $ in3 [31:0] $end
$var wire 32 % in4 [31:0] $end
$var wire 32 & in5 [31:0] $end
$var wire 32 ' in6 [31:0] $end
$var wire 32 ( in7 [31:0] $end
$var wire 32 ) in8 [31:0] $end
$var wire 32 * out1 [31:0] $end
$var wire 32 + out2 [31:0] $end
$var wire 32 , out3 [31:0] $end
$var wire 32 - out4 [31:0] $end
$var wire 1 . reset $end
$upscope $end
$upscope $end
$enddefinitions $end
#0
$dumpvars
1.
b0 -
b0 ,
b0 +
b0 *
bx )
bx (
bx '
bx &
bx %
bx $
bx #
bx "
1!
$end
#5000
0!
#10000
b0 )
b0 %
b0 (
b0 $
b0 '
b0 #
b0 &
b0 "
1!
#15000
0!
0.
#20000
1!
#25000
0!
#30000
b1101 &
b100 "
1!
#35000
0!
#40000
b1110 '
b1000 #
b1001 &
b11 "
1!
#45000
0!
#50000
b1111 (
b1100 $
b1010 '
b111 #
b101 &
b10 "
1!
#55000
0!
#60000
b10000 )
b10000 %
b1011 (
b1011 $
b110 '
b110 #
b1 &
b1 "
1!
#65000
0!
#70000
b1100 )
b1111 %
b111 (
b1010 $
b10 '
b101 #
b0 &
b0 "
b1101 *
1!
#75000
0!
#80000
b1001 *
b1110 +
b1000 )
b1110 %
b11 (
b1001 $
b0 '
b0 #
1!
#85000
0!
#90000
b100 )
b1101 %
b0 (
b0 $
b1111 ,
b1010 +
b101 *
1!
#95000
0!
#100000
b1 *
b110 +
b1011 ,
b10000 -
b0 )
b0 %
1!
#105000
0!
#110000
b1100 -
b111 ,
b10 +
b0 *
1!
#115000
0!
#120000
b0 +
b11 ,
b1000 -
1!
#125000
0!
#130000
b100 -
b0 ,
1!
