SIGMA/xbar.v
/////////////////////////////////////////////////////////////////////////

// Design: xbar.v
// Author: Eric Qin

// Basic Crossbar implmenetation for the distribution network.

/////////////////////////////////////////////////////////////////////////

module xbar # (
	parameter DATA_TYPE = 16,
	parameter NUM_PES = 4,
	parameter INPUT_BW = 4,
	parameter LOG2_PES = 2) (
	clk,   
	rst,
	i_data_bus, // input data bus
	i_mux_bus, // mux select control bus
	o_dist_bus // output bus to the multipliers
);

	input clk;
	input rst;
	input [INPUT_BW*DATA_TYPE-1 : 0] i_data_bus;
	input [LOG2_PES * NUM_PES -1 : 0] i_mux_bus;
	
	output reg [NUM_PES * DATA_TYPE -1 : 0] o_dist_bus;
	
	wire [NUM_PES * DATA_TYPE -1 : 0] w_dist_bus;
	
	genvar i;
	generate
		for (i=0; i < NUM_PES; i=i+1) begin : gen_out
			mux # (
				.DATA_TYPE(DATA_TYPE),
				.INPUT_BW(INPUT_BW),
				.SEL_SIZE(LOG2_PES)) my_mux (
				.clk(clk),
				.rst(rst),
				.i_data_bus(i_data_bus),
				.i_mux_sel(i_mux_bus[i*LOG2_PES+:LOG2_PES]),
				.o_dist(w_dist_bus[i*DATA_TYPE+:DATA_TYPE])
			);
		end   
	endgenerate
	
	always @ (posedge clk) begin
		o_dist_bus = w_dist_bus;
	end
	
endmodule

module mux # (
	parameter DATA_TYPE = 16,
	parameter INPUT_BW = 128,
	parameter SEL_SIZE = 7) (
	clk,
	rst,
	i_data_bus,
	i_mux_sel,
	o_dist
);
	input clk;
	input rst;
	input [INPUT_BW*DATA_TYPE-1 : 0] i_data_bus;
	input [SEL_SIZE-1 : 0] i_mux_sel;
	
	output reg [DATA_TYPE-1 : 0] o_dist;
	
	always @ (*) begin
		o_dist = i_data_bus[i_mux_sel*DATA_TYPE+:DATA_TYPE];
	end
	
endmodule

SIGMA/xbar_syn_tb.v
    `timescale 1ns / 1ps
    //////////////////////////////////////////////////////////////////////////////////
    // Company: 
    // Engineer: 
    // 
    // Create Date: 02.03.2021 17:17:40
    // Design Name: 
    // Module Name: tb_crossbar
    // Project Name: 
    // Target Devices: 
    // Tool Versions: 
    // Description: 
    // 
    // Dependencies: 
    // 
    // Revision:
    // Revision 0.01 - File Created
    // Additional Comments:
    // 
    //////////////////////////////////////////////////////////////////////////////////


    module tb_crossbar;
        parameter DATA_TYPE = 16;
        parameter NUM_PES = 16;
        parameter INPUT_BW = 16;
        parameter LOG2_PES = 4;
        parameter NUM_TESTS = 4;
        reg clk;
        reg rst;
        reg [INPUT_BW*DATA_TYPE-1 : 0] i_data_bus;
        reg [LOG2_PES * NUM_PES -1 : 0] i_mux_bus;
        
        wire [NUM_PES * DATA_TYPE -1 : 0] o_dist_bus;
        
            reg [10:0] counter = 'd0;

        xbar my_xbar_1 (
            .clk(clk),
            .rst(rst),
            .i_data_bus(i_data_bus),
            .i_mux_bus(i_mux_bus),
            .o_dist_bus(o_dist_bus)
        );
        
        initial begin
        $dumpfile ("xbar_iv_16syn.vcd");
        $dumpvars;
        rst = 1;
        clk = 0;
        #5
        rst = 0;
        #18 $finish;
        end
        
	always
	   #1 clk = ~clk;
// 	reg [(NUM_PES * DATA_TYPE * NUM_TESTS)-1 : 0] i_data_list_bus =
// 		{
// //            64'h3F80_4000_4040_4080_40A0_40C0_40E0_4100_4110_4120_4130_4140_4150_4160_4170_4180, // 1 2 3 4 5 6 7 8 
//             64'h3F80_4000_4040_4080, // 1 2 3 4 5 6 7 8 
// 			64'h40A0_40C0_40E0_4100,
// 			64'h4110_4120_4130_4140,
// 			64'h4150_4160_4170_4180};
	
	reg [(NUM_PES * DATA_TYPE * NUM_TESTS)-1 : 0] i_data_list_bus =
		{
            256'h3F80_4000_4040_4080_40A0_40C0_40E0_4100_4110_4120_4130_4140_4150_4160_4170_4180, // 1 2 3 4 5 6 7 8 
			256'h3F80_40A0_4110_4150_0000_0000_0000_0000_0000_0000_0000_0000_0000_0000_0000_0000,
			256'h4000_40C0_4120_4160_0000_0000_0000_0000_0000_0000_0000_0000_0000_0000_0000_0000,
			256'h4040_40E0_4130_4170_0000_0000_0000_0000_0000_0000_0000_0000_0000_0000_0000_0000};
	//*
    /*	
    reg [(NUM_PES * LOG2_PES *NUM_TESTS)-1:0] i_dest_bus =
		{
			8'b11_10_01_00, // stationary
			8'b11_10_01_00, // streaming
			8'b11_10_01_00, // streaming
			8'b11_10_01_00};	
	*/
	reg [(NUM_PES * LOG2_PES * NUM_TESTS)-1 : 0] i_dest_bus =
		{
			64'b1111_1110_1101_1100_1011_1010_1001_1000_0111_0110_0101_0100_0011_0010_0001_0000, // stationary
			64'b1111_1110_1101_1100_1111_1110_1101_1100_1111_1110_1101_1100_1111_1110_1101_1100, // streaming
			64'b1111_1110_1101_1100_1111_1110_1101_1100_1111_1110_1101_1100_1111_1110_1101_1100, // streaming
			64'b1111_1110_1101_1100_1111_1110_1101_1100_1111_1110_1101_1100_1111_1110_1101_1100};
			//*/		
    always @ (posedge clk) begin
		if (rst == 1'b0 && counter < NUM_TESTS) begin
			i_data_bus = i_data_list_bus[counter*(INPUT_BW*DATA_TYPE) +: (INPUT_BW*DATA_TYPE)];
			i_mux_bus = i_dest_bus[counter*(LOG2_PES * NUM_PES) +: (LOG2_PES * NUM_PES)];
			if (counter < NUM_TESTS) begin
				counter = counter + 1'b1;
			end
		end else begin
			i_data_bus = 'd0;
			i_mux_bus = 'd0;
		end
	end
	
	
endmodule

SIGMA/xbar_iv_16.vcd
$date
	Thu Apr 15 10:08:55 2021
$end
$version
	Icarus Verilog
$end
$timescale
	1ps
$end
$scope module tb_crossbar $end
$var wire 256 ! o_dist_bus [255:0] $end
$var reg 1 " clk $end
$var reg 11 # counter [10:0] $end
$var reg 256 $ i_data_bus [255:0] $end
$var reg 1024 % i_data_list_bus [1023:0] $end
$var reg 256 & i_dest_bus [255:0] $end
$var reg 64 ' i_mux_bus [63:0] $end
$var reg 1 ( rst $end
$scope module my_xbar_1 $end
$var wire 1 " clk $end
$var wire 256 ) i_data_bus [255:0] $end
$var wire 64 * i_mux_bus [63:0] $end
$var wire 1 ( rst $end
$var wire 256 + w_dist_bus [255:0] $end
$var reg 256 , o_dist_bus [255:0] $end
$scope begin gen_out[0] $end
$scope module my_mux $end
$var wire 1 " clk $end
$var wire 256 - i_data_bus [255:0] $end
$var wire 4 . i_mux_sel [3:0] $end
$var wire 1 ( rst $end
$var reg 16 / o_dist [15:0] $end
$upscope $end
$upscope $end
$scope begin gen_out[1] $end
$scope module my_mux $end
$var wire 1 " clk $end
$var wire 256 0 i_data_bus [255:0] $end
$var wire 4 1 i_mux_sel [3:0] $end
$var wire 1 ( rst $end
$var reg 16 2 o_dist [15:0] $end
$upscope $end
$upscope $end
$scope begin gen_out[2] $end
$scope module my_mux $end
$var wire 1 " clk $end
$var wire 256 3 i_data_bus [255:0] $end
$var wire 4 4 i_mux_sel [3:0] $end
$var wire 1 ( rst $end
$var reg 16 5 o_dist [15:0] $end
$upscope $end
$upscope $end
$scope begin gen_out[3] $end
$scope module my_mux $end
$var wire 1 " clk $end
$var wire 256 6 i_data_bus [255:0] $end
$var wire 4 7 i_mux_sel [3:0] $end
$var wire 1 ( rst $end
$var reg 16 8 o_dist [15:0] $end
$upscope $end
$upscope $end
$scope begin gen_out[4] $end
$scope module my_mux $end
$var wire 1 " clk $end
$var wire 256 9 i_data_bus [255:0] $end
$var wire 4 : i_mux_sel [3:0] $end
$var wire 1 ( rst $end
$var reg 16 ; o_dist [15:0] $end
$upscope $end
$upscope $end
$scope begin gen_out[5] $end
$scope module my_mux $end
$var wire 1 " clk $end
$var wire 256 < i_data_bus [255:0] $end
$var wire 4 = i_mux_sel [3:0] $end
$var wire 1 ( rst $end
$var reg 16 > o_dist [15:0] $end
$upscope $end
$upscope $end
$scope begin gen_out[6] $end
$scope module my_mux $end
$var wire 1 " clk $end
$var wire 256 ? i_data_bus [255:0] $end
$var wire 4 @ i_mux_sel [3:0] $end
$var wire 1 ( rst $end
$var reg 16 A o_dist [15:0] $end
$upscope $end
$upscope $end
$scope begin gen_out[7] $end
$scope module my_mux $end
$var wire 1 " clk $end
$var wire 256 B i_data_bus [255:0] $end
$var wire 4 C i_mux_sel [3:0] $end
$var wire 1 ( rst $end
$var reg 16 D o_dist [15:0] $end
$upscope $end
$upscope $end
$scope begin gen_out[8] $end
$scope module my_mux $end
$var wire 1 " clk $end
$var wire 256 E i_data_bus [255:0] $end
$var wire 4 F i_mux_sel [3:0] $end
$var wire 1 ( rst $end
$var reg 16 G o_dist [15:0] $end
$upscope $end
$upscope $end
$scope begin gen_out[9] $end
$scope module my_mux $end
$var wire 1 " clk $end
$var wire 256 H i_data_bus [255:0] $end
$var wire 4 I i_mux_sel [3:0] $end
$var wire 1 ( rst $end
$var reg 16 J o_dist [15:0] $end
$upscope $end
$upscope $end
$scope begin gen_out[10] $end
$scope module my_mux $end
$var wire 1 " clk $end
$var wire 256 K i_data_bus [255:0] $end
$var wire 4 L i_mux_sel [3:0] $end
$var wire 1 ( rst $end
$var reg 16 M o_dist [15:0] $end
$upscope $end
$upscope $end
$scope begin gen_out[11] $end
$scope module my_mux $end
$var wire 1 " clk $end
$var wire 256 N i_data_bus [255:0] $end
$var wire 4 O i_mux_sel [3:0] $end
$var wire 1 ( rst $end
$var reg 16 P o_dist [15:0] $end
$upscope $end
$upscope $end
$scope begin gen_out[12] $end
$scope module my_mux $end
$var wire 1 " clk $end
$var wire 256 Q i_data_bus [255:0] $end
$var wire 4 R i_mux_sel [3:0] $end
$var wire 1 ( rst $end
$var reg 16 S o_dist [15:0] $end
$upscope $end
$upscope $end
$scope begin gen_out[13] $end
$scope module my_mux $end
$var wire 1 " clk $end
$var wire 256 T i_data_bus [255:0] $end
$var wire 4 U i_mux_sel [3:0] $end
$var wire 1 ( rst $end
$var reg 16 V o_dist [15:0] $end
$upscope $end
$upscope $end
$scope begin gen_out[14] $end
$scope module my_mux $end
$var wire 1 " clk $end
$var wire 256 W i_data_bus [255:0] $end
$var wire 4 X i_mux_sel [3:0] $end
$var wire 1 ( rst $end
$var reg 16 Y o_dist [15:0] $end
$upscope $end
$upscope $end
$scope begin gen_out[15] $end
$scope module my_mux $end
$var wire 1 " clk $end
$var wire 256 Z i_data_bus [255:0] $end
$var wire 4 [ i_mux_sel [3:0] $end
$var wire 1 ( rst $end
$var reg 16 \ o_dist [15:0] $end
$upscope $end
$upscope $end
$upscope $end
$upscope $end
$enddefinitions $end
#0
$dumpvars
bx \
bx [
bx Z
bx Y
bx X
bx W
bx V
bx U
bx T
bx S
bx R
bx Q
bx P
bx O
bx N
bx M
bx L
bx K
bx J
bx I
bx H
bx G
bx F
bx E
bx D
bx C
bx B
bx A
bx @
bx ?
bx >
bx =
bx <
bx ;
bx :
bx 9
bx 8
bx 7
bx 6
bx 5
bx 4
bx 3
bx 2
bx 1
bx 0
bx /
bx .
bx -
bx ,
bx +
bx *
bx )
1(
bx '
b1111111011011100101110101001100001110110010101000011001000010000111111101101110011111110110111001111111011011100111111101101110011111110110111001111111011011100111111101101110011111110110111001111111011011100111111101101110011111110110111001111111011011100 &
b11111110000000010000000000000001000000010000000100000010000000010000001010000001000000110000000100000011100000010000010000000001000001000100000100000100100000010000010011000001000001010000000100000101010000010000010110000001000001011100000100000110000000001111111000000001000000101000000100000100010000010000010101000000000000000000000000000000000000000000000000000000000000000000000000000000000000000000000000000000000000000000000000000000000000000000000000000000000000000000000000000000000000000000000000000001000000000000000100000011000000010000010010000001000001011000000000000000000000000000000000000000000000000000000000000000000000000000000000000000000000000000000000000000000000000000000000000000000000000000000000000000000000000000000000000000000000000000000100000001000000010000001110000001000001001100000100000101110000000000000000000000000000000000000000000000000000000000000000000000000000000000000000000000000000000000000000000000000000000000000000000000000000000000000000000000000000000000000000000000000000 %
bx $
b0 #
0"
bx !
$end
#1000
b0 /
b0 2
b0 5
b0 8
b0 ;
b0 >
b0 A
b0 D
b0 G
b0 J
b0 M
b0 P
b0 S
b0 V
b0 Y
b0 +
b0 \
b0 .
b0 1
b0 4
b0 7
b0 :
b0 =
b0 @
b0 C
b0 F
b0 I
b0 L
b0 O
b0 R
b0 U
b0 X
b0 [
b0 '
b0 *
b0 $
b0 )
b0 -
b0 0
b0 3
b0 6
b0 9
b0 <
b0 ?
b0 B
b0 E
b0 H
b0 K
b0 N
b0 Q
b0 T
b0 W
b0 Z
1"
#2000
0"
#3000
b0 !
b0 ,
1"
#4000
0"
#5000
b100000101110000 /
b100000100110000 2
b100000011100000 5
b100000001000000 8
b100000101110000 ;
b100000100110000 >
b100000011100000 A
b100000001000000 D
b100000101110000 G
b100000100110000 J
b100000011100000 M
b100000001000000 P
b100000101110000 S
b100000100110000 V
b100000011100000 Y
b100000001000000010000001110000001000001001100000100000101110000010000000100000001000000111000000100000100110000010000010111000001000000010000000100000011100000010000010011000001000001011100000100000001000000010000001110000001000001001100000100000101110000 +
b100000001000000 \
b1100 .
b1101 1
b1110 4
b1111 7
b1100 :
b1101 =
b1110 @
b1111 C
b1100 F
b1101 I
b1110 L
b1111 O
b1100 R
b1101 U
b1110 X
b1111 [
b1 #
b1111111011011100111111101101110011111110110111001111111011011100 '
b1111111011011100111111101101110011111110110111001111111011011100 *
b100000001000000010000001110000001000001001100000100000101110000000000000000000000000000000000000000000000000000000000000000000000000000000000000000000000000000000000000000000000000000000000000000000000000000000000000000000000000000000000000000000000000000 $
b100000001000000010000001110000001000001001100000100000101110000000000000000000000000000000000000000000000000000000000000000000000000000000000000000000000000000000000000000000000000000000000000000000000000000000000000000000000000000000000000000000000000000 )
b100000001000000010000001110000001000001001100000100000101110000000000000000000000000000000000000000000000000000000000000000000000000000000000000000000000000000000000000000000000000000000000000000000000000000000000000000000000000000000000000000000000000000 -
b100000001000000010000001110000001000001001100000100000101110000000000000000000000000000000000000000000000000000000000000000000000000000000000000000000000000000000000000000000000000000000000000000000000000000000000000000000000000000000000000000000000000000 0
b100000001000000010000001110000001000001001100000100000101110000000000000000000000000000000000000000000000000000000000000000000000000000000000000000000000000000000000000000000000000000000000000000000000000000000000000000000000000000000000000000000000000000 3
b100000001000000010000001110000001000001001100000100000101110000000000000000000000000000000000000000000000000000000000000000000000000000000000000000000000000000000000000000000000000000000000000000000000000000000000000000000000000000000000000000000000000000 6
b100000001000000010000001110000001000001001100000100000101110000000000000000000000000000000000000000000000000000000000000000000000000000000000000000000000000000000000000000000000000000000000000000000000000000000000000000000000000000000000000000000000000000 9
b100000001000000010000001110000001000001001100000100000101110000000000000000000000000000000000000000000000000000000000000000000000000000000000000000000000000000000000000000000000000000000000000000000000000000000000000000000000000000000000000000000000000000 <
b100000001000000010000001110000001000001001100000100000101110000000000000000000000000000000000000000000000000000000000000000000000000000000000000000000000000000000000000000000000000000000000000000000000000000000000000000000000000000000000000000000000000000 ?
b100000001000000010000001110000001000001001100000100000101110000000000000000000000000000000000000000000000000000000000000000000000000000000000000000000000000000000000000000000000000000000000000000000000000000000000000000000000000000000000000000000000000000 B
b100000001000000010000001110000001000001001100000100000101110000000000000000000000000000000000000000000000000000000000000000000000000000000000000000000000000000000000000000000000000000000000000000000000000000000000000000000000000000000000000000000000000000 E
b100000001000000010000001110000001000001001100000100000101110000000000000000000000000000000000000000000000000000000000000000000000000000000000000000000000000000000000000000000000000000000000000000000000000000000000000000000000000000000000000000000000000000 H
b100000001000000010000001110000001000001001100000100000101110000000000000000000000000000000000000000000000000000000000000000000000000000000000000000000000000000000000000000000000000000000000000000000000000000000000000000000000000000000000000000000000000000 K
b100000001000000010000001110000001000001001100000100000101110000000000000000000000000000000000000000000000000000000000000000000000000000000000000000000000000000000000000000000000000000000000000000000000000000000000000000000000000000000000000000000000000000 N
b100000001000000010000001110000001000001001100000100000101110000000000000000000000000000000000000000000000000000000000000000000000000000000000000000000000000000000000000000000000000000000000000000000000000000000000000000000000000000000000000000000000000000 Q
b100000001000000010000001110000001000001001100000100000101110000000000000000000000000000000000000000000000000000000000000000000000000000000000000000000000000000000000000000000000000000000000000000000000000000000000000000000000000000000000000000000000000000 T
b100000001000000010000001110000001000001001100000100000101110000000000000000000000000000000000000000000000000000000000000000000000000000000000000000000000000000000000000000000000000000000000000000000000000000000000000000000000000000000000000000000000000000 W
b100000001000000010000001110000001000001001100000100000101110000000000000000000000000000000000000000000000000000000000000000000000000000000000000000000000000000000000000000000000000000000000000000000000000000000000000000000000000000000000000000000000000000 Z
1"
0(
#6000
0"
#7000
b100000101100000 /
b100000100100000 2
b100000011000000 5
b100000000000000 8
b100000101100000 ;
b100000100100000 >
b100000011000000 A
b100000000000000 D
b100000101100000 G
b100000100100000 J
b100000011000000 M
b100000000000000 P
b100000101100000 S
b100000100100000 V
b100000011000000 Y
b100000000000000010000001100000001000001001000000100000101100000010000000000000001000000110000000100000100100000010000010110000001000000000000000100000011000000010000010010000001000001011000000100000000000000010000001100000001000001001000000100000101100000 +
b100000000000000 \
b10 #
b100000000000000010000001100000001000001001000000100000101100000000000000000000000000000000000000000000000000000000000000000000000000000000000000000000000000000000000000000000000000000000000000000000000000000000000000000000000000000000000000000000000000000 $
b100000000000000010000001100000001000001001000000100000101100000000000000000000000000000000000000000000000000000000000000000000000000000000000000000000000000000000000000000000000000000000000000000000000000000000000000000000000000000000000000000000000000000 )
b100000000000000010000001100000001000001001000000100000101100000000000000000000000000000000000000000000000000000000000000000000000000000000000000000000000000000000000000000000000000000000000000000000000000000000000000000000000000000000000000000000000000000 -
b100000000000000010000001100000001000001001000000100000101100000000000000000000000000000000000000000000000000000000000000000000000000000000000000000000000000000000000000000000000000000000000000000000000000000000000000000000000000000000000000000000000000000 0
b100000000000000010000001100000001000001001000000100000101100000000000000000000000000000000000000000000000000000000000000000000000000000000000000000000000000000000000000000000000000000000000000000000000000000000000000000000000000000000000000000000000000000 3
b100000000000000010000001100000001000001001000000100000101100000000000000000000000000000000000000000000000000000000000000000000000000000000000000000000000000000000000000000000000000000000000000000000000000000000000000000000000000000000000000000000000000000 6
b100000000000000010000001100000001000001001000000100000101100000000000000000000000000000000000000000000000000000000000000000000000000000000000000000000000000000000000000000000000000000000000000000000000000000000000000000000000000000000000000000000000000000 9
b100000000000000010000001100000001000001001000000100000101100000000000000000000000000000000000000000000000000000000000000000000000000000000000000000000000000000000000000000000000000000000000000000000000000000000000000000000000000000000000000000000000000000 <
b100000000000000010000001100000001000001001000000100000101100000000000000000000000000000000000000000000000000000000000000000000000000000000000000000000000000000000000000000000000000000000000000000000000000000000000000000000000000000000000000000000000000000 ?
b100000000000000010000001100000001000001001000000100000101100000000000000000000000000000000000000000000000000000000000000000000000000000000000000000000000000000000000000000000000000000000000000000000000000000000000000000000000000000000000000000000000000000 B
b100000000000000010000001100000001000001001000000100000101100000000000000000000000000000000000000000000000000000000000000000000000000000000000000000000000000000000000000000000000000000000000000000000000000000000000000000000000000000000000000000000000000000 E
b100000000000000010000001100000001000001001000000100000101100000000000000000000000000000000000000000000000000000000000000000000000000000000000000000000000000000000000000000000000000000000000000000000000000000000000000000000000000000000000000000000000000000 H
b100000000000000010000001100000001000001001000000100000101100000000000000000000000000000000000000000000000000000000000000000000000000000000000000000000000000000000000000000000000000000000000000000000000000000000000000000000000000000000000000000000000000000 K
b100000000000000010000001100000001000001001000000100000101100000000000000000000000000000000000000000000000000000000000000000000000000000000000000000000000000000000000000000000000000000000000000000000000000000000000000000000000000000000000000000000000000000 N
b100000000000000010000001100000001000001001000000100000101100000000000000000000000000000000000000000000000000000000000000000000000000000000000000000000000000000000000000000000000000000000000000000000000000000000000000000000000000000000000000000000000000000 Q
b100000000000000010000001100000001000001001000000100000101100000000000000000000000000000000000000000000000000000000000000000000000000000000000000000000000000000000000000000000000000000000000000000000000000000000000000000000000000000000000000000000000000000 T
b100000000000000010000001100000001000001001000000100000101100000000000000000000000000000000000000000000000000000000000000000000000000000000000000000000000000000000000000000000000000000000000000000000000000000000000000000000000000000000000000000000000000000 W
b100000000000000010000001100000001000001001000000100000101100000000000000000000000000000000000000000000000000000000000000000000000000000000000000000000000000000000000000000000000000000000000000000000000000000000000000000000000000000000000000000000000000000 Z
b100000001000000010000001110000001000001001100000100000101110000010000000100000001000000111000000100000100110000010000010111000001000000010000000100000011100000010000010011000001000001011100000100000001000000010000001110000001000001001100000100000101110000 !
b100000001000000010000001110000001000001001100000100000101110000010000000100000001000000111000000100000100110000010000010111000001000000010000000100000011100000010000010011000001000001011100000100000001000000010000001110000001000001001100000100000101110000 ,
1"
#8000
0"
#9000
b100000101010000 /
b100000100010000 2
b100000010100000 5
b11111110000000 8
b100000101010000 ;
b100000100010000 >
b100000010100000 A
b11111110000000 D
b100000101010000 G
b100000100010000 J
b100000010100000 M
b11111110000000 P
b100000101010000 S
b100000100010000 V
b100000010100000 Y
b11111110000000010000001010000001000001000100000100000101010000001111111000000001000000101000000100000100010000010000010101000000111111100000000100000010100000010000010001000001000001010100000011111110000000010000001010000001000001000100000100000101010000 +
b11111110000000 \
b100000000000000010000001100000001000001001000000100000101100000010000000000000001000000110000000100000100100000010000010110000001000000000000000100000011000000010000010010000001000001011000000100000000000000010000001100000001000001001000000100000101100000 !
b100000000000000010000001100000001000001001000000100000101100000010000000000000001000000110000000100000100100000010000010110000001000000000000000100000011000000010000010010000001000001011000000100000000000000010000001100000001000001001000000100000101100000 ,
b11 #
b11111110000000010000001010000001000001000100000100000101010000000000000000000000000000000000000000000000000000000000000000000000000000000000000000000000000000000000000000000000000000000000000000000000000000000000000000000000000000000000000000000000000000 $
b11111110000000010000001010000001000001000100000100000101010000000000000000000000000000000000000000000000000000000000000000000000000000000000000000000000000000000000000000000000000000000000000000000000000000000000000000000000000000000000000000000000000000 )
b11111110000000010000001010000001000001000100000100000101010000000000000000000000000000000000000000000000000000000000000000000000000000000000000000000000000000000000000000000000000000000000000000000000000000000000000000000000000000000000000000000000000000 -
b11111110000000010000001010000001000001000100000100000101010000000000000000000000000000000000000000000000000000000000000000000000000000000000000000000000000000000000000000000000000000000000000000000000000000000000000000000000000000000000000000000000000000 0
b11111110000000010000001010000001000001000100000100000101010000000000000000000000000000000000000000000000000000000000000000000000000000000000000000000000000000000000000000000000000000000000000000000000000000000000000000000000000000000000000000000000000000 3
b11111110000000010000001010000001000001000100000100000101010000000000000000000000000000000000000000000000000000000000000000000000000000000000000000000000000000000000000000000000000000000000000000000000000000000000000000000000000000000000000000000000000000 6
b11111110000000010000001010000001000001000100000100000101010000000000000000000000000000000000000000000000000000000000000000000000000000000000000000000000000000000000000000000000000000000000000000000000000000000000000000000000000000000000000000000000000000 9
b11111110000000010000001010000001000001000100000100000101010000000000000000000000000000000000000000000000000000000000000000000000000000000000000000000000000000000000000000000000000000000000000000000000000000000000000000000000000000000000000000000000000000 <
b11111110000000010000001010000001000001000100000100000101010000000000000000000000000000000000000000000000000000000000000000000000000000000000000000000000000000000000000000000000000000000000000000000000000000000000000000000000000000000000000000000000000000 ?
b11111110000000010000001010000001000001000100000100000101010000000000000000000000000000000000000000000000000000000000000000000000000000000000000000000000000000000000000000000000000000000000000000000000000000000000000000000000000000000000000000000000000000 B
b11111110000000010000001010000001000001000100000100000101010000000000000000000000000000000000000000000000000000000000000000000000000000000000000000000000000000000000000000000000000000000000000000000000000000000000000000000000000000000000000000000000000000 E
b11111110000000010000001010000001000001000100000100000101010000000000000000000000000000000000000000000000000000000000000000000000000000000000000000000000000000000000000000000000000000000000000000000000000000000000000000000000000000000000000000000000000000 H
b11111110000000010000001010000001000001000100000100000101010000000000000000000000000000000000000000000000000000000000000000000000000000000000000000000000000000000000000000000000000000000000000000000000000000000000000000000000000000000000000000000000000000 K
b11111110000000010000001010000001000001000100000100000101010000000000000000000000000000000000000000000000000000000000000000000000000000000000000000000000000000000000000000000000000000000000000000000000000000000000000000000000000000000000000000000000000000 N
b11111110000000010000001010000001000001000100000100000101010000000000000000000000000000000000000000000000000000000000000000000000000000000000000000000000000000000000000000000000000000000000000000000000000000000000000000000000000000000000000000000000000000 Q
b11111110000000010000001010000001000001000100000100000101010000000000000000000000000000000000000000000000000000000000000000000000000000000000000000000000000000000000000000000000000000000000000000000000000000000000000000000000000000000000000000000000000000 T
b11111110000000010000001010000001000001000100000100000101010000000000000000000000000000000000000000000000000000000000000000000000000000000000000000000000000000000000000000000000000000000000000000000000000000000000000000000000000000000000000000000000000000 W
b11111110000000010000001010000001000001000100000100000101010000000000000000000000000000000000000000000000000000000000000000000000000000000000000000000000000000000000000000000000000000000000000000000000000000000000000000000000000000000000000000000000000000 Z
1"
#10000
0"
#11000
b100000101010000 8
b100000100010000 D
b100000010100000 P
b0 .
b1 1
b10 4
b11 7
b100 :
b101 =
b110 @
b111 C
b1000 F
b1001 I
b1010 L
b1011 O
b100000110000000 /
b100000101110000 2
b100000101100000 5
b100000101000000 ;
b100000100110000 >
b100000100100000 A
b100000100000000 G
b100000011100000 J
b100000011000000 M
b100000010000000 S
b100000001000000 V
b11111110000000010000000000000001000000010000000100000010000000010000001010000001000000110000000100000011100000010000010000000001000001000100000100000100100000010000010011000001000001010000000100000101010000010000010110000001000001011100000100000110000000 +
b100000000000000 Y
b100 #
b1111111011011100101110101001100001110110010101000011001000010000 '
b1111111011011100101110101001100001110110010101000011001000010000 *
b11111110000000010000000000000001000000010000000100000010000000010000001010000001000000110000000100000011100000010000010000000001000001000100000100000100100000010000010011000001000001010000000100000101010000010000010110000001000001011100000100000110000000 $
b11111110000000010000000000000001000000010000000100000010000000010000001010000001000000110000000100000011100000010000010000000001000001000100000100000100100000010000010011000001000001010000000100000101010000010000010110000001000001011100000100000110000000 )
b11111110000000010000000000000001000000010000000100000010000000010000001010000001000000110000000100000011100000010000010000000001000001000100000100000100100000010000010011000001000001010000000100000101010000010000010110000001000001011100000100000110000000 -
b11111110000000010000000000000001000000010000000100000010000000010000001010000001000000110000000100000011100000010000010000000001000001000100000100000100100000010000010011000001000001010000000100000101010000010000010110000001000001011100000100000110000000 0
b11111110000000010000000000000001000000010000000100000010000000010000001010000001000000110000000100000011100000010000010000000001000001000100000100000100100000010000010011000001000001010000000100000101010000010000010110000001000001011100000100000110000000 3
b11111110000000010000000000000001000000010000000100000010000000010000001010000001000000110000000100000011100000010000010000000001000001000100000100000100100000010000010011000001000001010000000100000101010000010000010110000001000001011100000100000110000000 6
b11111110000000010000000000000001000000010000000100000010000000010000001010000001000000110000000100000011100000010000010000000001000001000100000100000100100000010000010011000001000001010000000100000101010000010000010110000001000001011100000100000110000000 9
b11111110000000010000000000000001000000010000000100000010000000010000001010000001000000110000000100000011100000010000010000000001000001000100000100000100100000010000010011000001000001010000000100000101010000010000010110000001000001011100000100000110000000 <
b11111110000000010000000000000001000000010000000100000010000000010000001010000001000000110000000100000011100000010000010000000001000001000100000100000100100000010000010011000001000001010000000100000101010000010000010110000001000001011100000100000110000000 ?
b11111110000000010000000000000001000000010000000100000010000000010000001010000001000000110000000100000011100000010000010000000001000001000100000100000100100000010000010011000001000001010000000100000101010000010000010110000001000001011100000100000110000000 B
b11111110000000010000000000000001000000010000000100000010000000010000001010000001000000110000000100000011100000010000010000000001000001000100000100000100100000010000010011000001000001010000000100000101010000010000010110000001000001011100000100000110000000 E
b11111110000000010000000000000001000000010000000100000010000000010000001010000001000000110000000100000011100000010000010000000001000001000100000100000100100000010000010011000001000001010000000100000101010000010000010110000001000001011100000100000110000000 H
b11111110000000010000000000000001000000010000000100000010000000010000001010000001000000110000000100000011100000010000010000000001000001000100000100000100100000010000010011000001000001010000000100000101010000010000010110000001000001011100000100000110000000 K
b11111110000000010000000000000001000000010000000100000010000000010000001010000001000000110000000100000011100000010000010000000001000001000100000100000100100000010000010011000001000001010000000100000101010000010000010110000001000001011100000100000110000000 N
b11111110000000010000000000000001000000010000000100000010000000010000001010000001000000110000000100000011100000010000010000000001000001000100000100000100100000010000010011000001000001010000000100000101010000010000010110000001000001011100000100000110000000 Q
b11111110000000010000000000000001000000010000000100000010000000010000001010000001000000110000000100000011100000010000010000000001000001000100000100000100100000010000010011000001000001010000000100000101010000010000010110000001000001011100000100000110000000 T
b11111110000000010000000000000001000000010000000100000010000000010000001010000001000000110000000100000011100000010000010000000001000001000100000100000100100000010000010011000001000001010000000100000101010000010000010110000001000001011100000100000110000000 W
b11111110000000010000000000000001000000010000000100000010000000010000001010000001000000110000000100000011100000010000010000000001000001000100000100000100100000010000010011000001000001010000000100000101010000010000010110000001000001011100000100000110000000 Z
b11111110000000010000001010000001000001000100000100000101010000001111111000000001000000101000000100000100010000010000010101000000111111100000000100000010100000010000010001000001000001010100000011111110000000010000001010000001000001000100000100000101010000 !
b11111110000000010000001010000001000001000100000100000101010000001111111000000001000000101000000100000100010000010000010101000000111111100000000100000010100000010000010001000001000001010100000011111110000000010000001010000001000001000100000100000101010000 ,
1"
#12000
0"
#13000
b0 1
b0 4
b0 7
b0 :
b0 =
b0 @
b0 C
b0 F
b0 I
b0 L
b0 O
b0 R
b0 U
b0 X
b0 [
b0 /
b0 2
b0 5
b0 8
b0 ;
b0 >
b0 A
b0 D
b0 G
b0 J
b0 M
b0 P
b0 S
b0 V
b0 Y
b0 +
b0 \
b11111110000000010000000000000001000000010000000100000010000000010000001010000001000000110000000100000011100000010000010000000001000001000100000100000100100000010000010011000001000001010000000100000101010000010000010110000001000001011100000100000110000000 !
b11111110000000010000000000000001000000010000000100000010000000010000001010000001000000110000000100000011100000010000010000000001000001000100000100000100100000010000010011000001000001010000000100000101010000010000010110000001000001011100000100000110000000 ,
b0 '
b0 *
b0 $
b0 )
b0 -
b0 0
b0 3
b0 6
b0 9
b0 <
b0 ?
b0 B
b0 E
b0 H
b0 K
b0 N
b0 Q
b0 T
b0 W
b0 Z
1"
#14000
0"
#15000
b0 !
b0 ,
1"
