SIGMA/xbar.v
/////////////////////////////////////////////////////////////////////////

// Design: xbar.v
// Author: Eric Qin

// Basic Crossbar implmenetation for the distribution network.

/////////////////////////////////////////////////////////////////////////

module xbar # (
	parameter DATA_TYPE = 16,
	parameter NUM_PES = 4,
	parameter INPUT_BW = 4,
	parameter LOG2_PES = 2) (
	clk,   
	rst,
	i_data_bus, // input data bus
	i_mux_bus, // mux select control bus
	o_dist_bus // output bus to the multipliers
);

	input clk;
	input rst;
	input [INPUT_BW*DATA_TYPE-1 : 0] i_data_bus;
	input [LOG2_PES * NUM_PES -1 : 0] i_mux_bus;
	
	output reg [NUM_PES * DATA_TYPE -1 : 0] o_dist_bus;
	
	wire [NUM_PES * DATA_TYPE -1 : 0] w_dist_bus;
	
	genvar i;
	generate
		for (i=0; i < NUM_PES; i=i+1) begin : gen_out
			mux # (
				.DATA_TYPE(DATA_TYPE),
				.INPUT_BW(INPUT_BW),
				.SEL_SIZE(LOG2_PES)) my_mux (
				.clk(clk),
				.rst(rst),
				.i_data_bus(i_data_bus),
				.i_mux_sel(i_mux_bus[i*LOG2_PES+:LOG2_PES]),
				.o_dist(w_dist_bus[i*DATA_TYPE+:DATA_TYPE])
			);
		end   
	endgenerate
	
	always @ (posedge clk) begin
		o_dist_bus = w_dist_bus;
	end
	
endmodule

module mux # (
	parameter DATA_TYPE = 16,
	parameter INPUT_BW = 128,
	parameter SEL_SIZE = 7) (
	clk,
	rst,
	i_data_bus,
	i_mux_sel,
	o_dist
);
	input clk;
	input rst;
	input [INPUT_BW*DATA_TYPE-1 : 0] i_data_bus;
	input [SEL_SIZE-1 : 0] i_mux_sel;
	
	output reg [DATA_TYPE-1 : 0] o_dist;
	
	always @ (*) begin
		o_dist = i_data_bus[i_mux_sel*DATA_TYPE+:DATA_TYPE];
	end
	
endmodule

SIGMA/xbar_tb.v
    `timescale 1ns / 1ps
    //////////////////////////////////////////////////////////////////////////////////
    // Company: 
    // Engineer: 
    // 
    // Create Date: 02.03.2021 17:17:40
    // Design Name: 
    // Module Name: tb_crossbar
    // Project Name: 
    // Target Devices: 
    // Tool Versions: 
    // Description: 
    // 
    // Dependencies: 
    // 
    // Revision:
    // Revision 0.01 - File Created
    // Additional Comments:
    // 
    //////////////////////////////////////////////////////////////////////////////////


    module tb_crossbar;
        parameter DATA_TYPE = 16;
        parameter NUM_PES = 16;
        parameter INPUT_BW = 16;
        parameter LOG2_PES = 4;
        parameter NUM_TESTS = 4;
        reg clk;
        reg rst;
        reg [INPUT_BW*DATA_TYPE-1 : 0] i_data_bus;
        reg [LOG2_PES * NUM_PES -1 : 0] i_mux_bus;
        
        wire [NUM_PES * DATA_TYPE -1 : 0] o_dist_bus;
        
            reg [10:0] counter = 'd0;

        xbar #(
            .DATA_TYPE(DATA_TYPE),
            .NUM_PES(NUM_PES),
            .INPUT_BW(NUM_PES),
            .LOG2_PES(LOG2_PES))
            my_xbar_1 (
            .clk(clk),
            .rst(rst),
            .i_data_bus(i_data_bus),
            .i_mux_bus(i_mux_bus),
            .o_dist_bus(o_dist_bus)
        );
        
        initial begin
        $dumpfile ("xbar_iv_16_syn.vcd");
        $dumpvars;
        rst = 1;
        clk = 0;
        #5
        rst = 0;
        #65 $finish;
        end
        
	always
	   #1 clk = ~clk;
// 	reg [(NUM_PES * DATA_TYPE * NUM_TESTS)-1 : 0] i_data_list_bus =
// 		{
// //            64'h3F80_4000_4040_4080_40A0_40C0_40E0_4100_4110_4120_4130_4140_4150_4160_4170_4180, // 1 2 3 4 5 6 7 8 
//             64'h3F80_4000_4040_4080, // 1 2 3 4 5 6 7 8 
// 			64'h40A0_40C0_40E0_4100,
// 			64'h4110_4120_4130_4140,
// 			64'h4150_4160_4170_4180};
	
	reg [(NUM_PES * DATA_TYPE * NUM_TESTS)-1 : 0] i_data_list_bus =
		{
            256'h3F80_4000_4040_4080_40A0_40C0_40E0_4100_4110_4120_4130_4140_4150_4160_4170_4180, // 1 2 3 4 5 6 7 8 
			256'h3F80_40A0_4110_4150_0000_0000_0000_0000_0000_0000_0000_0000_0000_0000_0000_0000,
			256'h4000_40C0_4120_4160_0000_0000_0000_0000_0000_0000_0000_0000_0000_0000_0000_0000,
			256'h4040_40E0_4130_4170_0000_0000_0000_0000_0000_0000_0000_0000_0000_0000_0000_0000};
	//*
    /*	
    reg [(NUM_PES * LOG2_PES *NUM_TESTS)-1:0] i_dest_bus =
		{
			8'b11_10_01_00, // stationary
			8'b11_10_01_00, // streaming
			8'b11_10_01_00, // streaming
			8'b11_10_01_00};	
	*/
	reg [(NUM_PES * DATA_TYPE * NUM_TESTS)-1 : 0] i_dest_bus =
		{
			64'b1111_1110_1101_1100_1011_1010_1001_1000_0111_0110_0101_0100_0011_0010_0001_0000, // stationary
			64'b1111_1110_1101_1100_1111_1110_1101_1100_1111_1110_1101_1100_1111_1110_1101_1100, // streaming
			64'b1111_1110_1101_1100_1111_1110_1101_1100_1111_1110_1101_1100_1111_1110_1101_1100, // streaming
			64'b1111_1110_1101_1100_1111_1110_1101_1100_1111_1110_1101_1100_1111_1110_1101_1100};
			//*/		
    always @ (posedge clk) begin
		if (rst == 1'b0 && counter < NUM_TESTS) begin
			i_data_bus = i_data_list_bus[counter*64 +: 64];
			i_mux_bus = i_dest_bus[counter*8 +: 8];
			if (counter < NUM_TESTS) begin
				counter = counter + 1'b1;
			end
		end else begin
			i_data_bus = 'd0;
			i_mux_bus = 'd0;
		end
	end
	
	
endmodule

SIGMA/xbar_iv2.vcd
$date
	Tue Apr 13 09:58:56 2021
$end
$version
	Icarus Verilog
$end
$timescale
	1ps
$end
$scope module tb_crossbar $end
$scope module my_xbar_1 $end
$var wire 1 ! clk $end
$var wire 64 " i_data_bus [63:0] $end
$var wire 8 # i_mux_bus [7:0] $end
$var wire 1 $ rst $end
$var wire 64 % w_dist_bus [63:0] $end
$var reg 64 & o_dist_bus [63:0] $end
$upscope $end
$upscope $end
$enddefinitions $end
#0
$dumpvars
bx &
bx %
1$
bx #
bx "
0!
$end
#1000
b0 %
b0 #
b0 "
1!
#2000
0!
#3000
b0 &
1!
#4000
0!
#5000
b100000101010000010000010110000001000001011100000100000110000000 %
b11100100 #
b100000101010000010000010110000001000001011100000100000110000000 "
1!
0$
#6000
0!
#7000
b100000100010000010000010010000001000001001100000100000101000000 %
b100000100010000010000010010000001000001001100000100000101000000 "
b100000101010000010000010110000001000001011100000100000110000000 &
1!
#8000
0!
#9000
b100000010100000010000001100000001000000111000000100000100000000 %
b100000100010000010000010010000001000001001100000100000101000000 &
b100000010100000010000001100000001000000111000000100000100000000 "
1!
#10000
0!
#11000
b11111110000000010000000000000001000000010000000100000010000000 %
b11111110000000010000000000000001000000010000000100000010000000 "
b100000010100000010000001100000001000000111000000100000100000000 &
1!
#12000
0!
#13000
b0 %
b11111110000000010000000000000001000000010000000100000010000000 &
b0 #
b0 "
1!
#14000
0!
#15000
b0 &
1!
