SIGMA/xbar.v
/////////////////////////////////////////////////////////////////////////

// Design: xbar.v
// Author: Eric Qin

// Basic Crossbar implmenetation for the distribution network.

/////////////////////////////////////////////////////////////////////////

module xbar # (
	parameter DATA_TYPE = 16,
	parameter NUM_PES = 4,
	parameter INPUT_BW = 4,
	parameter LOG2_PES = 2) (
	clk,   
	rst,
	i_data_bus, // input data bus
	i_mux_bus, // mux select control bus
	o_dist_bus // output bus to the multipliers
);

	input clk;
	input rst;
	input [INPUT_BW*DATA_TYPE-1 : 0] i_data_bus;
	input [LOG2_PES * NUM_PES -1 : 0] i_mux_bus;
	
	output reg [NUM_PES * DATA_TYPE -1 : 0] o_dist_bus;
	
	wire [NUM_PES * DATA_TYPE -1 : 0] w_dist_bus;
	
	genvar i;
	generate
		for (i=0; i < NUM_PES; i=i+1) begin : gen_out
			mux # (
				.DATA_TYPE(DATA_TYPE),
				.INPUT_BW(INPUT_BW),
				.SEL_SIZE(LOG2_PES)) my_mux (
				.clk(clk),
				.rst(rst),
				.i_data_bus(i_data_bus),
				.i_mux_sel(i_mux_bus[i*LOG2_PES+:LOG2_PES]),
				.o_dist(w_dist_bus[i*DATA_TYPE+:DATA_TYPE])
			);
		end   
	endgenerate
	
	always @ (posedge clk) begin
		o_dist_bus = w_dist_bus;
	end
	
endmodule

module mux # (
	parameter DATA_TYPE = 16,
	parameter INPUT_BW = 128,
	parameter SEL_SIZE = 7) (
	clk,
	rst,
	i_data_bus,
	i_mux_sel,
	o_dist
);
	input clk;
	input rst;
	input [INPUT_BW*DATA_TYPE-1 : 0] i_data_bus;
	input [SEL_SIZE-1 : 0] i_mux_sel;
	
	output reg [DATA_TYPE-1 : 0] o_dist;
	
	always @ (*) begin
		o_dist = i_data_bus[i_mux_sel*DATA_TYPE+:DATA_TYPE];
	end
	
endmodule

SIGMA/xbar_tb.v
    `timescale 1ns / 1ps
    //////////////////////////////////////////////////////////////////////////////////
    // Company: 
    // Engineer: 
    // 
    // Create Date: 02.03.2021 17:17:40
    // Design Name: 
    // Module Name: tb_crossbar
    // Project Name: 
    // Target Devices: 
    // Tool Versions: 
    // Description: 
    // 
    // Dependencies: 
    // 
    // Revision:
    // Revision 0.01 - File Created
    // Additional Comments:
    // 
    //////////////////////////////////////////////////////////////////////////////////


    module tb_crossbar;
        parameter DATA_TYPE = 16;
        parameter NUM_PES = 16;
        parameter INPUT_BW = 16;
        parameter LOG2_PES = 4;
        parameter NUM_TESTS = 4;
        reg clk;
        reg rst;
        reg [INPUT_BW*DATA_TYPE-1 : 0] i_data_bus;
        reg [LOG2_PES * NUM_PES -1 : 0] i_mux_bus;
        
        wire [NUM_PES * DATA_TYPE -1 : 0] o_dist_bus;
        
            reg [10:0] counter = 'd0;

        xbar #(
            .DATA_TYPE(DATA_TYPE),
            .NUM_PES(NUM_PES),
            .INPUT_BW(NUM_PES),
            .LOG2_PES(LOG2_PES))
            my_xbar_1 (
            .clk(clk),
            .rst(rst),
            .i_data_bus(i_data_bus),
            .i_mux_bus(i_mux_bus),
            .o_dist_bus(o_dist_bus)
        );
        
        initial begin
        $dumpfile ("xbar_iv_16_syn.vcd");
        $dumpvars;
        rst = 1;
        clk = 0;
        #5
        rst = 0;
        #65 $finish;
        end
        
	always
	   #1 clk = ~clk;
// 	reg [(NUM_PES * DATA_TYPE * NUM_TESTS)-1 : 0] i_data_list_bus =
// 		{
// //            64'h3F80_4000_4040_4080_40A0_40C0_40E0_4100_4110_4120_4130_4140_4150_4160_4170_4180, // 1 2 3 4 5 6 7 8 
//             64'h3F80_4000_4040_4080, // 1 2 3 4 5 6 7 8 
// 			64'h40A0_40C0_40E0_4100,
// 			64'h4110_4120_4130_4140,
// 			64'h4150_4160_4170_4180};
	
	reg [(NUM_PES * DATA_TYPE * NUM_TESTS)-1 : 0] i_data_list_bus =
		{
            256'h3F80_4000_4040_4080_40A0_40C0_40E0_4100_4110_4120_4130_4140_4150_4160_4170_4180, // 1 2 3 4 5 6 7 8 
			256'h3F80_40A0_4110_4150_0000_0000_0000_0000_0000_0000_0000_0000_0000_0000_0000_0000,
			256'h4000_40C0_4120_4160_0000_0000_0000_0000_0000_0000_0000_0000_0000_0000_0000_0000,
			256'h4040_40E0_4130_4170_0000_0000_0000_0000_0000_0000_0000_0000_0000_0000_0000_0000};
	//*
    /*	
    reg [(NUM_PES * LOG2_PES *NUM_TESTS)-1:0] i_dest_bus =
		{
			8'b11_10_01_00, // stationary
			8'b11_10_01_00, // streaming
			8'b11_10_01_00, // streaming
			8'b11_10_01_00};	
	*/
	reg [(NUM_PES * DATA_TYPE * NUM_TESTS)-1 : 0] i_dest_bus =
		{
			64'b1111_1110_1101_1100_1011_1010_1001_1000_0111_0110_0101_0100_0011_0010_0001_0000, // stationary
			64'b1111_1110_1101_1100_1111_1110_1101_1100_1111_1110_1101_1100_1111_1110_1101_1100, // streaming
			64'b1111_1110_1101_1100_1111_1110_1101_1100_1111_1110_1101_1100_1111_1110_1101_1100, // streaming
			64'b1111_1110_1101_1100_1111_1110_1101_1100_1111_1110_1101_1100_1111_1110_1101_1100};
			//*/		
    always @ (posedge clk) begin
		if (rst == 1'b0 && counter < NUM_TESTS) begin
			i_data_bus = i_data_list_bus[counter*64 +: 64];
			i_mux_bus = i_dest_bus[counter*8 +: 8];
			if (counter < NUM_TESTS) begin
				counter = counter + 1'b1;
			end
		end else begin
			i_data_bus = 'd0;
			i_mux_bus = 'd0;
		end
	end
	
	
endmodule

xbar_iv_16_syn.vcd
$date
   Thu Apr 15 10:23:49 2021
$end
$version
  2019.2
$end
$timescale
  1ps
$end
$scope module tb_crossbar $end
$var reg 1 ! clk $end
$var reg 1 " rst $end
$var reg 256 # i_data_bus [255:0] $end
$var reg 64 $ i_mux_bus [63:0] $end
$var wire 256 % o_dist_bus [255:0] $end
$var reg 11 & counter [10:0] $end
$var reg 1024 ' i_data_list_bus [1023:0] $end
$var reg 256 ( i_dest_bus [255:0] $end
$var parameter 32 ) DATA_TYPE [31:0] $end
$var parameter 32 * NUM_PES [31:0] $end
$var parameter 32 + INPUT_BW [31:0] $end
$var parameter 32 , LOG2_PES [31:0] $end
$var parameter 32 - NUM_TESTS [31:0] $end
$scope module my_xbar_1 $end
$var wire 1 . clk $end
$var wire 1 / rst $end
$var wire 256 0 i_data_bus [255:0] $end
$var wire 64 1 i_mux_bus [63:0] $end
$var reg 256 2 o_dist_bus [255:0] $end
$var wire 256 3 w_dist_bus [255:0] $end
$var parameter 32 4 DATA_TYPE [31:0] $end
$var parameter 32 5 NUM_PES [31:0] $end
$var parameter 32 6 INPUT_BW [31:0] $end
$var parameter 32 7 LOG2_PES [31:0] $end
$scope module gen_out[0].my_mux $end
$var wire 1 . clk $end
$var wire 1 / rst $end
$var wire 256 0 i_data_bus [255:0] $end
$var wire 4 8 i_mux_sel [3:0] $end
$var reg 16 9 o_dist [15:0] $end
$var parameter 32 : DATA_TYPE [31:0] $end
$var parameter 32 ; INPUT_BW [31:0] $end
$var parameter 32 < SEL_SIZE [31:0] $end
$upscope $end
$scope module gen_out[1].my_mux $end
$var wire 1 . clk $end
$var wire 1 / rst $end
$var wire 256 0 i_data_bus [255:0] $end
$var wire 4 = i_mux_sel [3:0] $end
$var reg 16 > o_dist [15:0] $end
$var parameter 32 ? DATA_TYPE [31:0] $end
$var parameter 32 @ INPUT_BW [31:0] $end
$var parameter 32 A SEL_SIZE [31:0] $end
$upscope $end
$scope module gen_out[2].my_mux $end
$var wire 1 . clk $end
$var wire 1 / rst $end
$var wire 256 0 i_data_bus [255:0] $end
$var wire 4 B i_mux_sel [3:0] $end
$var reg 16 C o_dist [15:0] $end
$var parameter 32 D DATA_TYPE [31:0] $end
$var parameter 32 E INPUT_BW [31:0] $end
$var parameter 32 F SEL_SIZE [31:0] $end
$upscope $end
$scope module gen_out[3].my_mux $end
$var wire 1 . clk $end
$var wire 1 / rst $end
$var wire 256 0 i_data_bus [255:0] $end
$var wire 4 G i_mux_sel [3:0] $end
$var reg 16 H o_dist [15:0] $end
$var parameter 32 I DATA_TYPE [31:0] $end
$var parameter 32 J INPUT_BW [31:0] $end
$var parameter 32 K SEL_SIZE [31:0] $end
$upscope $end
$scope module gen_out[4].my_mux $end
$var wire 1 . clk $end
$var wire 1 / rst $end
$var wire 256 0 i_data_bus [255:0] $end
$var wire 4 L i_mux_sel [3:0] $end
$var reg 16 M o_dist [15:0] $end
$var parameter 32 N DATA_TYPE [31:0] $end
$var parameter 32 O INPUT_BW [31:0] $end
$var parameter 32 P SEL_SIZE [31:0] $end
$upscope $end
$scope module gen_out[5].my_mux $end
$var wire 1 . clk $end
$var wire 1 / rst $end
$var wire 256 0 i_data_bus [255:0] $end
$var wire 4 Q i_mux_sel [3:0] $end
$var reg 16 R o_dist [15:0] $end
$var parameter 32 S DATA_TYPE [31:0] $end
$var parameter 32 T INPUT_BW [31:0] $end
$var parameter 32 U SEL_SIZE [31:0] $end
$upscope $end
$scope module gen_out[6].my_mux $end
$var wire 1 . clk $end
$var wire 1 / rst $end
$var wire 256 0 i_data_bus [255:0] $end
$var wire 4 V i_mux_sel [3:0] $end
$var reg 16 W o_dist [15:0] $end
$var parameter 32 X DATA_TYPE [31:0] $end
$var parameter 32 Y INPUT_BW [31:0] $end
$var parameter 32 Z SEL_SIZE [31:0] $end
$upscope $end
$scope module gen_out[7].my_mux $end
$var wire 1 . clk $end
$var wire 1 / rst $end
$var wire 256 0 i_data_bus [255:0] $end
$var wire 4 [ i_mux_sel [3:0] $end
$var reg 16 \ o_dist [15:0] $end
$var parameter 32 ] DATA_TYPE [31:0] $end
$var parameter 32 ^ INPUT_BW [31:0] $end
$var parameter 32 _ SEL_SIZE [31:0] $end
$upscope $end
$scope module gen_out[8].my_mux $end
$var wire 1 . clk $end
$var wire 1 / rst $end
$var wire 256 0 i_data_bus [255:0] $end
$var wire 4 ` i_mux_sel [3:0] $end
$var reg 16 a o_dist [15:0] $end
$var parameter 32 b DATA_TYPE [31:0] $end
$var parameter 32 c INPUT_BW [31:0] $end
$var parameter 32 d SEL_SIZE [31:0] $end
$upscope $end
$scope module gen_out[9].my_mux $end
$var wire 1 . clk $end
$var wire 1 / rst $end
$var wire 256 0 i_data_bus [255:0] $end
$var wire 4 e i_mux_sel [3:0] $end
$var reg 16 f o_dist [15:0] $end
$var parameter 32 g DATA_TYPE [31:0] $end
$var parameter 32 h INPUT_BW [31:0] $end
$var parameter 32 i SEL_SIZE [31:0] $end
$upscope $end
$scope module gen_out[10].my_mux $end
$var wire 1 . clk $end
$var wire 1 / rst $end
$var wire 256 0 i_data_bus [255:0] $end
$var wire 4 j i_mux_sel [3:0] $end
$var reg 16 k o_dist [15:0] $end
$var parameter 32 l DATA_TYPE [31:0] $end
$var parameter 32 m INPUT_BW [31:0] $end
$var parameter 32 n SEL_SIZE [31:0] $end
$upscope $end
$scope module gen_out[11].my_mux $end
$var wire 1 . clk $end
$var wire 1 / rst $end
$var wire 256 0 i_data_bus [255:0] $end
$var wire 4 o i_mux_sel [3:0] $end
$var reg 16 p o_dist [15:0] $end
$var parameter 32 q DATA_TYPE [31:0] $end
$var parameter 32 r INPUT_BW [31:0] $end
$var parameter 32 s SEL_SIZE [31:0] $end
$upscope $end
$scope module gen_out[12].my_mux $end
$var wire 1 . clk $end
$var wire 1 / rst $end
$var wire 256 0 i_data_bus [255:0] $end
$var wire 4 t i_mux_sel [3:0] $end
$var reg 16 u o_dist [15:0] $end
$var parameter 32 v DATA_TYPE [31:0] $end
$var parameter 32 w INPUT_BW [31:0] $end
$var parameter 32 x SEL_SIZE [31:0] $end
$upscope $end
$scope module gen_out[13].my_mux $end
$var wire 1 . clk $end
$var wire 1 / rst $end
$var wire 256 0 i_data_bus [255:0] $end
$var wire 4 y i_mux_sel [3:0] $end
$var reg 16 z o_dist [15:0] $end
$var parameter 32 { DATA_TYPE [31:0] $end
$var parameter 32 | INPUT_BW [31:0] $end
$var parameter 32 } SEL_SIZE [31:0] $end
$upscope $end
$scope module gen_out[14].my_mux $end
$var wire 1 . clk $end
$var wire 1 / rst $end
$var wire 256 0 i_data_bus [255:0] $end
$var wire 4 ~ i_mux_sel [3:0] $end
$var reg 16 !! o_dist [15:0] $end
$var parameter 32 "! DATA_TYPE [31:0] $end
$var parameter 32 #! INPUT_BW [31:0] $end
$var parameter 32 $! SEL_SIZE [31:0] $end
$upscope $end
$scope module gen_out[15].my_mux $end
$var wire 1 . clk $end
$var wire 1 / rst $end
$var wire 256 0 i_data_bus [255:0] $end
$var wire 4 %! i_mux_sel [3:0] $end
$var reg 16 &! o_dist [15:0] $end
$var parameter 32 '! DATA_TYPE [31:0] $end
$var parameter 32 (! INPUT_BW [31:0] $end
$var parameter 32 )! SEL_SIZE [31:0] $end
$upscope $end
$upscope $end
$upscope $end
$enddefinitions $end
#0
$dumpvars
0!
bx !!
1"
b10000 "!
bx #
b10000 #!
bx $
b100 $!
bx %
bx %!
b0 &
bx &!
b11111110000000010000000000000001000000010000000100000010000000010000001010000001000000110000000100000011100000010000010000000001000001000100000100000100100000010000010011000001000001010000000100000101010000010000010110000001000001011100000100000110000000001111111000000001000000101000000100000100010000010000010101000000000000000000000000000000000000000000000000000000000000000000000000000000000000000000000000000000000000000000000000000000000000000000000000000000000000000000000000000000000000000000000000000001000000000000000100000011000000010000010010000001000001011000000000000000000000000000000000000000000000000000000000000000000000000000000000000000000000000000000000000000000000000000000000000000000000000000000000000000000000000000000000000000000000000000000100000001000000010000001110000001000001001100000100000101110000000000000000000000000000000000000000000000000000000000000000000000000000000000000000000000000000000000000000000000000000000000000000000000000000000000000000000000000000000000000000000000000000 '
b10000 '!
b1111111011011100101110101001100001110110010101000011001000010000111111101101110011111110110111001111111011011100111111101101110011111110110111001111111011011100111111101101110011111110110111001111111011011100111111101101110011111110110111001111111011011100 (
b10000 (!
b10000 )
b100 )!
b10000 *
b10000 +
b100 ,
b100 -
0.
1/
bx 0
bx 1
bx 2
bx 3
b10000 4
b10000 5
b10000 6
b100 7
bx 8
bx 9
b10000 :
b10000 ;
b100 <
bx =
bx >
b10000 ?
b10000 @
b100 A
bx B
bx C
b10000 D
b10000 E
b100 F
bx G
bx H
b10000 I
b10000 J
b100 K
bx L
bx M
b10000 N
b10000 O
b100 P
bx Q
bx R
b10000 S
b10000 T
b100 U
bx V
bx W
b10000 X
b10000 Y
b100 Z
bx [
bx \
b10000 ]
b10000 ^
b100 _
bx `
bx a
b10000 b
b10000 c
b100 d
bx e
bx f
b10000 g
b10000 h
b100 i
bx j
bx k
b10000 l
b10000 m
b100 n
bx o
bx p
b10000 q
b10000 r
b100 s
bx t
bx u
b10000 v
b10000 w
b100 x
bx y
bx z
b10000 {
b10000 |
b100 }
bx ~
$end
#1000
1!
b0 !!
b0 #
b0 $
b0 %!
b0 &!
1.
b0 0
b0 1
bx 2
b0 3
b0 8
b0 9
b0 =
b0 >
b0 B
b0 C
b0 G
b0 H
b0 L
b0 M
b0 Q
b0 R
b0 V
b0 W
b0 [
b0 \
b0 `
b0 a
b0 e
b0 f
b0 j
b0 k
b0 o
b0 p
b0 t
b0 u
b0 y
b0 z
b0 ~
#2000
0!
0.
#3000
1!
b0 #
b0 $
b0 %
1.
b0 2
#4000
0!
0.
#5000
1!
b100000011100000 !!
0"
b100000001000000010000001110000001000001001100000100000101110000000000000000000000000000000000000000000000000000000000000000000000000000000000000000000000000000000000000000000000000000000000000000000000000000000000000000000000000000000000000000000000000000 #
b1111111011011100111111101101110011111110110111001111111011011100 $
b1111 %!
b1 &
b100000001000000 &!
1.
0/
b100000001000000010000001110000001000001001100000100000101110000000000000000000000000000000000000000000000000000000000000000000000000000000000000000000000000000000000000000000000000000000000000000000000000000000000000000000000000000000000000000000000000000 0
b1111111011011100111111101101110011111110110111001111111011011100 1
b0 2
b100000001000000010000001110000001000001001100000100000101110000010000000100000001000000111000000100000100110000010000010111000001000000010000000100000011100000010000010011000001000001011100000100000001000000010000001110000001000001001100000100000101110000 3
b1100 8
b100000101110000 9
b1101 =
b100000100110000 >
b1110 B
b100000011100000 C
b1111 G
b100000001000000 H
b1100 L
b100000101110000 M
b1101 Q
b100000100110000 R
b1110 V
b100000011100000 W
b1111 [
b100000001000000 \
b1100 `
b100000101110000 a
b1101 e
b100000100110000 f
b1110 j
b100000011100000 k
b1111 o
b100000001000000 p
b1100 t
b100000101110000 u
b1101 y
b100000100110000 z
b1110 ~
#6000
0!
0.
#7000
1!
b100000011000000 !!
b100000000000000010000001100000001000001001000000100000101100000000000000000000000000000000000000000000000000000000000000000000000000000000000000000000000000000000000000000000000000000000000000000000000000000000000000000000000000000000000000000000000000000 #
b1111111011011100111111101101110011111110110111001111111011011100 $
b100000001000000010000001110000001000001001100000100000101110000010000000100000001000000111000000100000100110000010000010111000001000000010000000100000011100000010000010011000001000001011100000100000001000000010000001110000001000001001100000100000101110000 %
b10 &
b100000000000000 &!
1.
b100000000000000010000001100000001000001001000000100000101100000000000000000000000000000000000000000000000000000000000000000000000000000000000000000000000000000000000000000000000000000000000000000000000000000000000000000000000000000000000000000000000000000 0
b100000001000000010000001110000001000001001100000100000101110000010000000100000001000000111000000100000100110000010000010111000001000000010000000100000011100000010000010011000001000001011100000100000001000000010000001110000001000001001100000100000101110000 2
b100000000000000010000001100000001000001001000000100000101100000010000000000000001000000110000000100000100100000010000010110000001000000000000000100000011000000010000010010000001000001011000000100000000000000010000001100000001000001001000000100000101100000 3
b100000101100000 9
b100000100100000 >
b100000011000000 C
b100000000000000 H
b100000101100000 M
b100000100100000 R
b100000011000000 W
b100000000000000 \
b100000101100000 a
b100000100100000 f
b100000011000000 k
b100000000000000 p
b100000101100000 u
b100000100100000 z
#8000
0!
0.
#9000
1!
b100000010100000 !!
b11111110000000010000001010000001000001000100000100000101010000000000000000000000000000000000000000000000000000000000000000000000000000000000000000000000000000000000000000000000000000000000000000000000000000000000000000000000000000000000000000000000000000 #
b1111111011011100111111101101110011111110110111001111111011011100 $
b100000000000000010000001100000001000001001000000100000101100000010000000000000001000000110000000100000100100000010000010110000001000000000000000100000011000000010000010010000001000001011000000100000000000000010000001100000001000001001000000100000101100000 %
b11 &
b11111110000000 &!
1.
b11111110000000010000001010000001000001000100000100000101010000000000000000000000000000000000000000000000000000000000000000000000000000000000000000000000000000000000000000000000000000000000000000000000000000000000000000000000000000000000000000000000000000 0
b100000000000000010000001100000001000001001000000100000101100000010000000000000001000000110000000100000100100000010000010110000001000000000000000100000011000000010000010010000001000001011000000100000000000000010000001100000001000001001000000100000101100000 2
b11111110000000010000001010000001000001000100000100000101010000001111111000000001000000101000000100000100010000010000010101000000111111100000000100000010100000010000010001000001000001010100000011111110000000010000001010000001000001000100000100000101010000 3
b100000101010000 9
b100000100010000 >
b100000010100000 C
b11111110000000 H
b100000101010000 M
b100000100010000 R
b100000010100000 W
b11111110000000 \
b100000101010000 a
b100000100010000 f
b100000010100000 k
b11111110000000 p
b100000101010000 u
b100000100010000 z
#10000
0!
0.
#11000
1!
b100000000000000 !!
b11111110000000010000000000000001000000010000000100000010000000010000001010000001000000110000000100000011100000010000010000000001000001000100000100000100100000010000010011000001000001010000000100000101010000010000010110000001000001011100000100000110000000 #
b1111111011011100101110101001100001110110010101000011001000010000 $
b11111110000000010000001010000001000001000100000100000101010000001111111000000001000000101000000100000100010000010000010101000000111111100000000100000010100000010000010001000001000001010100000011111110000000010000001010000001000001000100000100000101010000 %
b1111 %!
b100 &
b11111110000000 &!
1.
b11111110000000010000000000000001000000010000000100000010000000010000001010000001000000110000000100000011100000010000010000000001000001000100000100000100100000010000010011000001000001010000000100000101010000010000010110000001000001011100000100000110000000 0
b1111111011011100101110101001100001110110010101000011001000010000 1
b11111110000000010000001010000001000001000100000100000101010000001111111000000001000000101000000100000100010000010000010101000000111111100000000100000010100000010000010001000001000001010100000011111110000000010000001010000001000001000100000100000101010000 2
b11111110000000010000000000000001000000010000000100000010000000010000001010000001000000110000000100000011100000010000010000000001000001000100000100000100100000010000010011000001000001010000000100000101010000010000010110000001000001011100000100000110000000 3
b0 8
b100000110000000 9
b1 =
b100000101110000 >
b10 B
b100000101100000 C
b11 G
b100000101010000 H
b100 L
b100000101000000 M
b101 Q
b100000100110000 R
b110 V
b100000100100000 W
b111 [
b100000100010000 \
b1000 `
b100000100000000 a
b1001 e
b100000011100000 f
b1010 j
b100000011000000 k
b1011 o
b100000010100000 p
b1100 t
b100000010000000 u
b1101 y
b100000001000000 z
b1110 ~
#12000
0!
0.
#13000
1!
b0 !!
b0 #
b0 $
b11111110000000010000000000000001000000010000000100000010000000010000001010000001000000110000000100000011100000010000010000000001000001000100000100000100100000010000010011000001000001010000000100000101010000010000010110000001000001011100000100000110000000 %
b0 %!
b0 &!
1.
b0 0
b0 1
b11111110000000010000000000000001000000010000000100000010000000010000001010000001000000110000000100000011100000010000010000000001000001000100000100000100100000010000010011000001000001010000000100000101010000010000010110000001000001011100000100000110000000 2
b0 3
b0 8
b0 9
b0 =
b0 >
b0 B
b0 C
b0 G
b0 H
b0 L
b0 M
b0 Q
b0 R
b0 V
b0 W
b0 [
b0 \
b0 `
b0 a
b0 e
b0 f
b0 j
b0 k
b0 o
b0 p
b0 t
b0 u
b0 y
b0 z
b0 ~
#14000
0!
0.
#15000
1!
b0 #
b0 $
b0 %
1.
b0 2
#16000
0!
0.
#17000
1!
b0 #
b0 $
1.
b0 2
#18000
0!
0.
#19000
1!
b0 #
b0 $
1.
b0 2
#20000
0!
0.
#21000
1!
b0 #
b0 $
1.
b0 2
#22000
0!
0.
#23000
1!
b0 #
b0 $
1.
b0 2
#24000
0!
0.
#25000
1!
b0 #
b0 $
1.
b0 2
#26000
0!
0.
#27000
1!
b0 #
b0 $
1.
b0 2
#28000
0!
0.
#29000
1!
b0 #
b0 $
1.
b0 2
#30000
0!
0.
#31000
1!
b0 #
b0 $
1.
b0 2
#32000
0!
0.
#33000
1!
b0 #
b0 $
1.
b0 2
#34000
0!
0.
#35000
1!
b0 #
b0 $
1.
b0 2
#36000
0!
0.
#37000
1!
b0 #
b0 $
1.
b0 2
#38000
0!
0.
#39000
1!
b0 #
b0 $
1.
b0 2
#40000
0!
0.
#41000
1!
b0 #
b0 $
1.
b0 2
#42000
0!
0.
#43000
1!
b0 #
b0 $
1.
b0 2
#44000
0!
0.
#45000
1!
b0 #
b0 $
1.
b0 2
#46000
0!
0.
#47000
1!
b0 #
b0 $
1.
b0 2
#48000
0!
0.
#49000
1!
b0 #
b0 $
1.
b0 2
#50000
0!
0.
#51000
1!
b0 #
b0 $
1.
b0 2
#52000
0!
0.
#53000
1!
b0 #
b0 $
1.
b0 2
#54000
0!
0.
#55000
1!
b0 #
b0 $
1.
b0 2
#56000
0!
0.
#57000
1!
b0 #
b0 $
1.
b0 2
#58000
0!
0.
#59000
1!
b0 #
b0 $
1.
b0 2
#60000
0!
0.
#61000
1!
b0 #
b0 $
1.
b0 2
#62000
0!
0.
#63000
1!
b0 #
b0 $
1.
b0 2
#64000
0!
0.
#65000
1!
b0 #
b0 $
1.
b0 2
#66000
0!
0.
#67000
1!
b0 #
b0 $
1.
b0 2
#68000
0!
0.
#69000
1!
b0 #
b0 $
1.
b0 2
